jupyterlab_irods/__init__.py
jupyterlab_irods/irods.py
jupyterlab_irods-3.0.5.dist-info/METADATA
jupyterlab_irods-3.0.5.dist-info/WHEEL
jupyterlab_irods-3.0.5.dist-info/top_level.txt
jupyterlab_irods-3.0.5.dist-info/RECORD
