Metadata-Version: 2.1
Name: jupyterlab-irods
Version: 3.0.5
Summary: A Jupyter Notebook server extension which acts as a backend for IRODS requests.
Home-page: http://jupyter.org
Author: Todd Wickizer
Author-email: jupyter@googlegroups.com
License: BSD
Keywords: Jupyter,JupyterLab,Irods
Platform: Linux
Platform: Mac OS X
Platform: Windows
Classifier: Intended Audience :: Developers
Classifier: Intended Audience :: System Administrators
Classifier: Intended Audience :: Science/Research
Classifier: License :: OSI Approved :: BSD License
Classifier: Programming Language :: Python
Classifier: Programming Language :: Python :: 2.7
Classifier: Programming Language :: Python :: 3
Requires-Dist: notebook
Requires-Dist: python-irodsclient
